[
  {
    "timestamp": "2026-07-04T17:08:20.037353+00:00",
    "action": "SIGNAL",
    "signal": "NEUTRAL",
    "btc_dir": "up",
    "eb_dir": "up",
    "signal_strength": 1,
    "convergence_type": "BROAD_RALLY",
    "btc_price": 62862.9,
    "position_open": false
  },
  {
    "timestamp": "2026-07-04T17:10:23.932723+00:00",
    "action": "SIGNAL",
    "signal": "NEUTRAL",
    "btc_dir": "up",
    "eb_dir": "up",
    "signal_strength": 2,
    "convergence_type": "BROAD_RALLY",
    "btc_price": 62871.5,
    "position_open": false
  },
  {
    "timestamp": "2026-07-04T17:12:25.962857+00:00",
    "action": "SIGNAL",
    "signal": "NEUTRAL",
    "btc_dir": "up",
    "eb_dir": "up",
    "signal_strength": 2,
    "convergence_type": "BROAD_RALLY",
    "btc_price": 62869.1,
    "position_open": false
  },
  {
    "timestamp": "2026-07-04T17:14:23.305703+00:00",
    "action": "SIGNAL",
    "signal": "NEUTRAL",
    "btc_dir": "up",
    "eb_dir": "up",
    "signal_strength": 1,
    "convergence_type": "BROAD_RALLY",
    "btc_price": 62796.2,
    "position_open": false
  },
  {
    "timestamp": "2026-07-04T17:16:23.038779+00:00",
    "action": "SIGNAL",
    "signal": "LONG_BTC",
    "btc_dir": "up",
    "eb_dir": "dn",
    "signal_strength": 1,
    "convergence_type": "BTC_LEADS_UP",
    "btc_price": 62843.8,
    "position_open": false
  },
  {
    "timestamp": "2026-07-04T17:16:44.425556+00:00",
    "action": "OPEN",
    "signal": "LONG_BTC",
    "btc_side": "long",
    "eth_side": "short",
    "btc_size": 0.00159,
    "eth_size": 0.0562,
    "btc_entry_price": 62843.8,
    "eth_entry_price": 1779.86,
    "pnl": null,
    "trade_duration_minutes": null,
    "signal_strength": 1,
    "convergence_type": "BTC_LEADS_UP"
  },
  {
    "timestamp": "2026-07-04T17:18:23.357411+00:00",
    "action": "SIGNAL",
    "signal": "LONG_BTC",
    "btc_dir": "up",
    "eb_dir": "dn",
    "signal_strength": 2,
    "convergence_type": "BTC_LEADS_UP",
    "btc_price": 62834.2,
    "position_open": true
  },
  {
    "timestamp": "2026-07-04T17:20:29.121877+00:00",
    "action": "SIGNAL",
    "signal": "LONG_BTC",
    "btc_dir": "up",
    "eb_dir": "dn",
    "signal_strength": 2,
    "convergence_type": "BTC_LEADS_UP",
    "btc_price": 62857.6,
    "position_open": true
  },
  {
    "timestamp": "2026-07-04T17:22:22.333989+00:00",
    "action": "SIGNAL",
    "signal": "LONG_BTC",
    "btc_dir": "up",
    "eb_dir": "dn",
    "signal_strength": 1,
    "convergence_type": "BTC_LEADS_UP",
    "btc_price": 62870.9,
    "position_open": true
  },
  {
    "timestamp": "2026-07-04T17:22:27.705745+00:00",
    "action": "CLOSE",
    "signal": "LONG_BTC",
    "btc_side": "long",
    "eth_side": "short",
    "btc_size": 0.00159,
    "eth_size": 0.0562,
    "btc_entry_price": 62843.8,
    "eth_entry_price": 1779.86,
    "pnl": -0.1,
    "trade_duration_minutes": 5.7,
    "signal_strength": 1,
    "exit_reason": "POSITION_SYNC_MISMATCH",
    "peak_pnl": 0.036012999999992815,
    "peak_pnl_time": "2026-07-04 18:18 WAT",
    "convergence_type": "BTC_LEADS_UP"
  },
  {
    "timestamp": "2026-07-04T17:24:18.311630+00:00",
    "action": "SIGNAL",
    "signal": "LONG_BTC",
    "btc_dir": "up",
    "eb_dir": "dn",
    "signal_strength": 1,
    "convergence_type": "BTC_LEADS_UP",
    "btc_price": 62866.0,
    "position_open": false
  },
  {
    "timestamp": "2026-07-04T17:26:27.102191+00:00",
    "action": "SIGNAL",
    "signal": "LONG_BTC",
    "btc_dir": "up",
    "eb_dir": "dn",
    "signal_strength": 1,
    "convergence_type": "BTC_LEADS_UP",
    "btc_price": 62910.3,
    "position_open": false
  },
  {
    "timestamp": "2026-07-04T17:28:17.744074+00:00",
    "action": "SIGNAL",
    "signal": "LONG_BTC",
    "btc_dir": "up",
    "eb_dir": "dn",
    "signal_strength": 1,
    "convergence_type": "BTC_LEADS_UP",
    "btc_price": 62910.3,
    "position_open": false
  }
]