{
  "current_signal": "LONG_ETH",
  "position_open": true,
  "entry_btc_size": 0.00157,
  "entry_eth_size": 0.0559,
  "trade_count": 402,
  "last_run_utc": "2026-07-06T01:04:28.336208+00:00",
  "entry_time_utc": "2026-07-06T00:46:39.682666+00:00",
  "entry_btc_price": 63623.3,
  "entry_eth_price": 1789.09,
  "entry_equity": 11.333527998690009,
  "peak_pnl": 0.0752569986900076,
  "peak_pnl_time": "2026-07-06 02:04 WAT",
  "trail_active": true,
  "trail_flip_active": true,
  "last_flip_signal": "NEUTRAL",
  "last_known_pnl": 0.0752569986900076,
  "last_lag_alert_utc": "2026-07-05T14:00:27.246481+00:00",
  "open_signal": "LONG_ETH",
  "last_equity": 11.41440056175103,
  "last_avail": 1.3358591000000004,
  "last_unrealized_pnl": 0.0752569986900076,
  "equity_updated_utc": "2026-07-06T01:04:28.336201+00:00",
  "last_api_fail_utc": ""
}